{"_id":"022d455369b19e3e0034e7a33431930f","_openid":"omXRQ3dmY5PJI_GC6Xhood8SWozk","postId":"1cec055169adad0500ac23581b0072e6","content":"111","parentId":null,"authorInfo":{"_id":"omXRQ3dmY5PJI_GC6Xhood8SWozk","avatarUrl":"cloud://xiaowen-env-0gdw907s2b9957d2.7869-xiaowen-env-0gdw907s2b9957d2-1395855427/user-avatars/1773218551588_6119.jpg","nickname":"小文","verified":false},"likeCount":0,"createTime":{"$date":"2026-03-11T16:54:21.863Z"},"updateTime":{"$date":"2026-03-11T16:54:21.863Z"},"status":"active","replyCount":1}
{"_id":"7d9be0e169b2f0310055086815532639","_openid":"omXRQ3cXJtCvBTgTpnYbm6w2CT94","postId":"1cec055169adad0500ac23581b0072e6","parentId":"022d455369b19e3e0034e7a33431930f","content":"来来来","authorInfo":{"_id":"omXRQ3cXJtCvBTgTpnYbm6w2CT94","avatarUrl":"cloud://xiaowen-env-0gdw907s2b9957d2.7869-xiaowen-env-0gdw907s2b9957d2-1395855427/user-avatars/1772968968365_2938.jpg","nickname":"muliy"},"likeCount":0,"createTime":{"$date":"2026-03-12T16:56:17.142Z"},"updateTime":{"$date":"2026-03-12T16:56:17.142Z"},"status":"active"}
{"_id":"b3c6c3d569b704a9004f6bec0c08bf3d","_openid":"omXRQ3cXJtCvBTgTpnYbm6w2CT94","postId":"51caa21d69b40666006e26c20fda9327","content":"211","parentId":null,"authorInfo":{"_id":"omXRQ3cXJtCvBTgTpnYbm6w2CT94","avatarUrl":"cloud://xiaowen-env-0gdw907s2b9957d2.7869-xiaowen-env-0gdw907s2b9957d2-1395855427/user-avatars/1772968968365_2938.jpg","nickname":"muliy","verified":false},"likeCount":0,"createTime":{"$date":"2026-03-15T19:12:41.174Z"},"updateTime":{"$date":"2026-03-15T19:12:41.174Z"},"status":"active"}
